glow/__init__.py
glow/conftest.py
glow/conversions.py
glow/functions.py
glow/glow.py
glow/gwas/__init__.py
glow/gwas/approx_firth.py
glow/gwas/functions.py
glow/gwas/lin_reg.py
glow/gwas/log_reg.py
glow/logging/__init__.py
glow/logging/hlseventlogger.py
glow/sql/__init__.py
glow/sql/functions.py
glow/sql/tests/__init__.py
glow/sql/tests/test_overlap_join.py
glow/tests/__init__.py
glow/tests/test_conversions.py
glow/tests/test_register.py
glow/tests/test_transform.py
glow/wgr/__init__.py
glow/wgr/logistic_ridge_regression.py
glow/wgr/logistic_udfs.py
glow/wgr/model_functions.py
glow/wgr/ridge_reduction.py
glow/wgr/ridge_regression.py
glow/wgr/ridge_udfs.py
glow/wgr/wgr_functions.py
glow/wgr/tests/__init__.py
glow/wgr/tests/test_block_variants_and_samples.py
glow/wgr/tests/test_estimate_loco_offsets.py
glow/wgr/tests/test_functions.py
glow/wgr/tests/test_logistic_ridge_regression.py
glow/wgr/tests/test_reshape_for_gwas.py
glow/wgr/tests/test_ridge_regression.py
glow/wgr/tests/test_sample_id_extraction.py
glow.py-2.0.0.dist-info/LICENSE.txt
glow.py-2.0.0.dist-info/METADATA
glow.py-2.0.0.dist-info/WHEEL
glow.py-2.0.0.dist-info/top_level.txt
glow.py-2.0.0.dist-info/RECORD
