Metadata-Version: 2.1
Name: glow.py
Version: 2.0.0
Summary: An open-source toolkit for large-scale genomic analysis
Home-page: https://projectglow.io
Author: The Glow Authors
License: Apache License 2.0
Classifier: Intended Audience :: Developers
Classifier: Programming Language :: Python :: 3.7
License-File: LICENSE.txt
Requires-Dist: nptyping >=2.5.0
Requires-Dist: numpy >=1.23.5
Requires-Dist: opt-einsum >=3.2.0
Requires-Dist: pandas >=1.5.3
Requires-Dist: scipy >=1.10.0
Requires-Dist: statsmodels >=0.13.5
Requires-Dist: typeguard >=2.13.3
